interception_driver/__init__.py
interception_driver/constants.py
interception_driver/core.py
interception_driver/interception.dll
interception_driver/structures.py
interception_driver-0.1.1.dist-info/METADATA
interception_driver-0.1.1.dist-info/WHEEL
interception_driver-0.1.1.dist-info/top_level.txt
interception_driver-0.1.1.dist-info/RECORD
