Metadata-Version: 2.1
Name: interception-driver
Version: 0.1.1
Summary: Python wrapper for Interception driver (Low-level input)
Home-page: 
Author: Ibrahim Arslan
Author-email: ibrahimarslan226@gmail.com
Classifier: Programming Language :: Python :: 3
Classifier: Operating System :: Microsoft :: Windows
Classifier: Topic :: Software Development :: Libraries :: Python Modules
Requires-Python: >=3.6
